{"sidebar-1":{"search-2":{"title":""},"recent-posts-2":{"title":"","number":5},"recent-comments-2":{"title":"","number":5},"archives-2":{"title":"","count":0,"dropdown":0},"categories-2":{"title":"","count":0,"hierarchical":0,"dropdown":0},"meta-2":{"title":""},"recent-posts-3":{"title":"Recent News","number":3,"show_date":true},"tag_cloud-1":{"title":"Tags","taxonomy":"post_tag"}},"sidebar-pages":{"advanced_sidebar_menu-1":{"title":"","order_by":"menu_order","exclude":"","levels":"1"},"text-1":{"title":"Testimonials","text":"<img src=\"http:\/\/broker.commercegurus.com\/wp-content\/uploads\/2015\/10\/n_lopez.png\" alt=\"\" class=\"testimonial-pic\" \/>\r\n\r\n<blockquote>My firm has been greatly helped by the excellent work from Broker, you won\u2019t be disappointed.<\/blockquote>\r\n\r\n<cite>Nadia Lopez \u2014 Heuston, Texas<\/cite>","filter":false,"classes":"boxed testimonials","ids":null},"text-2":{"title":"Our Brochure","text":"<p>View our 2016 financial prospectus brochure for an easy to read guide on all of the services offer.<\/p>\r\n\r\n<p><a href=\"#\" class=\"pdf\">Download PDF<\/a><\/p>","filter":false,"classes":"boxed document","ids":null}},"top-bar-left":{"text-3":{"title":"","text":"Welcome to Broker Financial Services, we have over 20 years of expertise","filter":false}},"top-bar-right":{"text-4":{"title":"","text":"[date]","filter":false,"classes":"","ids":null}},"mobile-search":{"search-3":{"title":"","classes":"","ids":null}},"header-details":{"text-5":{"title":"07:30 - 19:00","text":"Monday to Friday\r\n<i class=\"ion-ios-time-outline\"><\/i>","filter":false},"text-6":{"title":"Goldsmith Hall,","text":"New York, NY 90210\r\n<i class=\"ion-ios-location-outline\"><\/i>","filter":false},"text-7":{"title":"1800 234 567","text":"<a href=\"#\">info@example.com<\/a>\r\n<i class=\"ion-ios-telephone-outline\"><\/i>","filter":false,"classes":"","ids":null}},"first-footer":{"text-8":{"title":"","text":"<img src=\"http:\/\/broker.commercegurus.com\/wp-content\/uploads\/2015\/10\/broker-logo-w.png\" class=\"logo\" alt=\"Broker Logo\" style=\"display: block; max-width: 180px; margin-bottom: 18px; margin-top: -4px;\" \/>\r\n\r\n<p style=\"margin-right: 10px;\">We provide expert financial advice to both individuals and businesses. With over 20 years of experience we\u2019ll ensure that you\u2019re always getting the best guidance from the most professional company in the industry.<\/p>","filter":false,"classes":"","ids":null},"text-9":{"title":"Explore","text":"<div class=\"row\">\r\n<div class=\"col-xs-6 col-sm-6 col-md-6\">\r\n<ul class=\"border\">\r\n<li><a href=\"#\">Home<\/a><\/li>\r\n<li><a href=\"#\">About Us<\/a><\/li>\r\n<li><a href=\"#\">Services<\/a><\/li>\r\n<li><a href=\"#\">Testimonials<\/a><\/li>\r\n<li><a href=\"#\">News<\/a><\/li>\r\n<li><a href=\"#\">Contact Us<\/a><\/li>\r\n<\/ul>\r\n<\/div>\r\n<div class=\"col-xs-6 col-sm-6 col-md-6\">\r\n<ul>\r\n<li><a href=\"#\">Bonds<\/a><\/li>\r\n<li><a href=\"#\">Commodities<\/a><\/li>\r\n<li><a href=\"#\">Investments<\/a><\/li>\r\n<li><a href=\"#\">Retirement<\/a><\/li>\r\n<li><a href=\"#\">Stocks<\/a><\/li>\r\n<li><a href=\"#\">Trades<\/a><\/li>\r\n<\/ul>\r\n<\/div>\r\n<\/div>","filter":false,"classes":"","ids":null},"recent-posts-4":{"title":"Recent News","number":2,"show_date":true},"text-10":{"title":"Our Newsletter","text":"[mc4wp_form]\r\n\r\n<hr\/>\r\n\r\n<a href=\"#\" class=\"theme-buy\">A Custom Link &nbsp; &rarr;<\/a>","filter":false,"classes":"","ids":null}},"second-footer":{"text-11":{"title":"","text":"<ul class=\"inline\">\r\n<li class=\"facebook\"><a href=\"#\">Facebook<\/a><\/li>\r\n<li class=\"twitter\"><a href=\"#\">Twitter<\/a><\/li>\r\n<li class=\"linkedin\"><a href=\"#\">LinkedIn<\/a><\/li>\r\n<li class=\"google-plus\"><a href=\"#\">Google+<\/a><\/li>\r\n<\/ul>","filter":false},"text-12":{"title":"","text":"<ul class=\"inline right\">\r\n<li><a href=\"#\">Legal<\/a><\/li>\r\n<li><a href=\"#\">Sitemap<\/a><\/li>\r\n<li><a href=\"#\">Privacy Policy<\/a><\/li>\r\n<\/ul>","filter":false,"classes":"","ids":null}}}